{
	"Items": [
		{
			"Rarity": "Abundant",
			"Id": "Phoenix_Tears_Small"
		},
		{
			"Rarity": "Uncommon",
			"Id": "Phoenix_Tears"
		},
		{
			"Rarity": "ExtremelyRare",
			"Id": "Zombie_Impersonator_Suit"
		}
	],
	"FixedItems": [
		"Copper_Coins",
		"Copper_Coins",
		"Copper_Coins",
		"Copper_Coins",
		"Copper_Coins"
	],
	"Probability": 10,
	"QuantityMin": 1,
	"QuantityMax": 1,
	"AllowDuplicates": false,
	"ShouldFilterItemsByZone": false,
	"InitialDamage": 50,
	"RandomDamage": 10,
	"PostSpawnActions": [
		"SetClothesDirtiness_ResidentialClothes"
	]
}